appstore_tools/__init__.py
appstore_tools/actions/__init__.py
appstore_tools/actions/download.py
appstore_tools/actions/list.py
appstore_tools/actions/publish.py
appstore_tools/actions/util.py
appstore_tools/appstore/__init__.py
appstore_tools/appstore/api.py
appstore_tools/appstore/auth.py
appstore_tools/appstore/exceptions.py
appstore_tools/appstore/fetch.py
appstore_tools/appstore/types.py
appstore_tools/appstore/util.py
appstore_tools/console.py
appstore_tools/console_actions.py
appstore_tools/print_util.py
appstore_tools/tqdm_util.py
appstore_tools/version.py
appstore_tools-0.1.8.dist-info/entry_points.txt
appstore_tools-0.1.8.dist-info/LICENSE
appstore_tools-0.1.8.dist-info/WHEEL
appstore_tools-0.1.8.dist-info/METADATA
appstore_tools-0.1.8.dist-info/RECORD
